skydict/__init__.py
skydict/types/__init__.py
skydict-1.0.4.dist-info/LICENSE
skydict-1.0.4.dist-info/METADATA
skydict-1.0.4.dist-info/WHEEL
skydict-1.0.4.dist-info/top_level.txt
skydict-1.0.4.dist-info/RECORD
